[
  {
    "id": "lead_1779725034946",
    "name": "Workflow Test",
    "phone": "+212600000006",
    "email": "",
    "interest": "commande",
    "message": "Commande ord_1779725034945_0h4h3mfek — Robe Caftan — 4500 MAD",
    "status": "new",
    "createdAt": "2026-05-25T16:03:54.945Z"
  },
  {
    "id": "lead_1779725034697_ul8l55iwr",
    "name": "E2E Test User",
    "phone": "+212600000004",
    "email": "e2e@test.com",
    "interest": "caftan",
    "message": "This is an automated E2E test",
    "status": "new",
    "createdAt": "2026-05-25T16:03:54.697Z"
  },
  {
    "id": "lead_1779725031036",
    "name": "Test Customer",
    "phone": "+212600000002",
    "email": "customer@example.com",
    "interest": "commande",
    "message": "Commande ord_1779725031035_ijmzy8qh6 — Robe Caftan Édition Limitée — 4500 MAD",
    "status": "new",
    "createdAt": "2026-05-25T16:03:51.035Z"
  },
  {
    "id": "lead_1779725030989_g22v1oxri",
    "name": "Test Lead",
    "phone": "+212600000001",
    "email": "test@example.com",
    "interest": "caftan",
    "message": "E2E test message",
    "status": "new",
    "createdAt": "2026-05-25T16:03:50.989Z"
  },
  {
    "id": "lead_1779724972839",
    "name": "Workflow Test",
    "phone": "+212600000006",
    "email": "",
    "interest": "commande",
    "message": "Commande ord_1779724972838_saep0qdp4 — Robe Caftan — 4500 MAD",
    "status": "new",
    "createdAt": "2026-05-25T16:02:52.838Z"
  },
  {
    "id": "lead_1779724972549_z276kncke",
    "name": "E2E Test User",
    "phone": "+212600000004",
    "email": "e2e@test.com",
    "interest": "caftan",
    "message": "This is an automated E2E test",
    "status": "new",
    "createdAt": "2026-05-25T16:02:52.549Z"
  },
  {
    "id": "lead_1779724969313",
    "name": "Test Customer",
    "phone": "+212600000002",
    "email": "customer@example.com",
    "interest": "commande",
    "message": "Commande ord_1779724969313_uwn3x0x57 — Robe Caftan Édition Limitée — 4500 MAD",
    "status": "new",
    "createdAt": "2026-05-25T16:02:49.313Z"
  },
  {
    "id": "lead_1779724969275_rtpd2weyu",
    "name": "Test Lead",
    "phone": "+212600000001",
    "email": "test@example.com",
    "interest": "caftan",
    "message": "E2E test message",
    "status": "new",
    "createdAt": "2026-05-25T16:02:49.275Z"
  },
  {
    "id": "lead_1779723659176",
    "name": "Workflow Test",
    "phone": "+212600000006",
    "email": "",
    "interest": "commande",
    "message": "Commande ord_1779723659175_oy1xnohbt — Robe Caftan — 4500 MAD",
    "status": "new",
    "createdAt": "2026-05-25T15:40:59.175Z"
  },
  {
    "id": "lead_1779723658857_81de3axu3",
    "name": "E2E Test User",
    "phone": "+212600000004",
    "email": "e2e@test.com",
    "interest": "caftan",
    "message": "This is an automated E2E test",
    "status": "new",
    "createdAt": "2026-05-25T15:40:58.857Z"
  },
  {
    "id": "lead_1779723655678",
    "name": "Test Customer",
    "phone": "+212600000002",
    "email": "customer@example.com",
    "interest": "commande",
    "message": "Commande ord_1779723655677_7bb1hz21n — Robe Caftan Édition Limitée — 4500 MAD",
    "status": "new",
    "createdAt": "2026-05-25T15:40:55.677Z"
  },
  {
    "id": "lead_1779723655628_j392hiiv6",
    "name": "Test Lead",
    "phone": "+212600000001",
    "email": "test@example.com",
    "interest": "caftan",
    "message": "E2E test message",
    "status": "new",
    "createdAt": "2026-05-25T15:40:55.628Z"
  },
  {
    "id": "lead_1779723530766",
    "name": "Workflow Test",
    "phone": "+212600000006",
    "email": "",
    "interest": "commande",
    "message": "Commande ord_1779723530765_nij50y4oq — Robe Caftan — 4500 MAD",
    "status": "new",
    "createdAt": "2026-05-25T15:38:50.765Z"
  },
  {
    "id": "lead_1779723530278_ocejxvkud",
    "name": "E2E Test User",
    "phone": "+212600000004",
    "email": "e2e@test.com",
    "interest": "caftan",
    "message": "This is an automated E2E test",
    "status": "new",
    "createdAt": "2026-05-25T15:38:50.278Z"
  },
  {
    "id": "lead_1779723527236",
    "name": "Test Customer",
    "phone": "+212600000002",
    "email": "customer@example.com",
    "interest": "commande",
    "message": "Commande ord_1779723527235_5pxioggtu — Robe Caftan Édition Limitée — 4500 MAD",
    "status": "new",
    "createdAt": "2026-05-25T15:38:47.236Z"
  },
  {
    "id": "lead_1779723527203_w79l6jbr2",
    "name": "Test Lead",
    "phone": "+212600000001",
    "email": "test@example.com",
    "interest": "caftan",
    "message": "E2E test message",
    "status": "new",
    "createdAt": "2026-05-25T15:38:47.203Z"
  },
  {
    "id": "lead_1779723273299",
    "name": "Workflow Test",
    "phone": "+212600000006",
    "email": "",
    "interest": "commande",
    "message": "Commande ord_1779723273298_m9heisavg — Robe Caftan — 4500 MAD",
    "status": "new",
    "createdAt": "2026-05-25T15:34:33.298Z"
  },
  {
    "id": "lead_1779723273000_9mdciuk60",
    "name": "E2E Test User",
    "phone": "+212600000004",
    "email": "e2e@test.com",
    "interest": "caftan",
    "message": "This is an automated E2E test",
    "status": "new",
    "createdAt": "2026-05-25T15:34:33.000Z"
  },
  {
    "id": "lead_1779723269663",
    "name": "Test Customer",
    "phone": "+212600000002",
    "email": "customer@example.com",
    "interest": "commande",
    "message": "Commande ord_1779723269663_03dq3f83y — Robe Caftan Édition Limitée — 4500 MAD",
    "status": "new",
    "createdAt": "2026-05-25T15:34:29.663Z"
  },
  {
    "id": "lead_1779723269616_cseqmrx28",
    "name": "Test Lead",
    "phone": "+212600000001",
    "email": "test@example.com",
    "interest": "caftan",
    "message": "E2E test message",
    "status": "new",
    "createdAt": "2026-05-25T15:34:29.617Z"
  },
  {
    "id": "lead_1779723133755",
    "name": "Workflow Test",
    "phone": "+212600000006",
    "email": "",
    "interest": "commande",
    "message": "Commande ord_1779723133755_lim9mvxfi — Robe Caftan — 4500 MAD",
    "status": "new",
    "createdAt": "2026-05-25T15:32:13.755Z"
  },
  {
    "id": "lead_1779723103514_y13bsqwhs",
    "name": "Test Lead",
    "phone": "+212600000001",
    "email": "test@example.com",
    "interest": "caftan",
    "message": "E2E test message",
    "status": "new",
    "createdAt": "2026-05-25T15:31:43.514Z"
  },
  {
    "id": "lead_1779723102382",
    "name": "Test Customer",
    "phone": "+212600000002",
    "email": "customer@example.com",
    "interest": "commande",
    "message": "Commande ord_1779723102381_o78dvu57s — Robe Caftan Édition Limitée — 4500 MAD",
    "status": "new",
    "createdAt": "2026-05-25T15:31:42.382Z"
  },
  {
    "id": "lead_1779723032215",
    "name": "Workflow Test",
    "phone": "+212600000006",
    "email": "",
    "interest": "commande",
    "message": "Commande ord_1779723032214_eh1329goh — Robe Caftan — 4500 MAD",
    "status": "new",
    "createdAt": "2026-05-25T15:30:32.215Z"
  },
  {
    "id": "lead_1779723000500",
    "name": "Test Customer",
    "phone": "+212600000002",
    "email": "customer@example.com",
    "interest": "commande",
    "message": "Commande ord_1779723000499_6jwsq2kv1 — Robe Caftan Édition Limitée — 4500 MAD",
    "status": "new",
    "createdAt": "2026-05-25T15:30:00.499Z"
  },
  {
    "id": "lead_1779723000382_0eaztemzi",
    "name": "Test Lead",
    "phone": "+212600000001",
    "email": "test@example.com",
    "interest": "caftan",
    "message": "E2E test message",
    "status": "new",
    "createdAt": "2026-05-25T15:30:00.382Z"
  }
]